<?xml version="1.0" encoding="utf-8"?>
<openerp>
    <data>
        <record id="transportation_reason_VEN" model="stock.picking.transportation_reason">
            <field name="name">Sale</field>
            <field name="to_be_invoiced">1</field>
        </record>
        <record id="transportation_reason_VIS" model="stock.picking.transportation_reason">
            <field name="name">Goods on approval</field>
        </record>
        <record id="transportation_reason_RES" model="stock.picking.transportation_reason">
            <field name="name">Returned</field>
        </record>
     </data>
</openerp>
